clinput
