Metadata-Version: 2.1
Name: clinput
Version: 1.0.2
Summary: Useful command line input functions with error checking.
Home-page: https://github.com/cameronmccormack/clinput
Author: Cameron McCormack
Author-email: cam.mac@live.co.uk
License: UNKNOWN
Project-URL: Bug Reports, https://github.com/cameronmccormack/clinput/issues
Project-URL: Source, https://github.com/cameronmccormack/clinput
Keywords: command line input
Platform: UNKNOWN
Classifier: Development Status :: 3 - Alpha
Classifier: Intended Audience :: Developers
Classifier: License :: OSI Approved :: MIT License
Classifier: Programming Language :: Python :: 3
Classifier: Programming Language :: Python :: 3.5
Classifier: Programming Language :: Python :: 3.6
Classifier: Programming Language :: Python :: 3.7
Requires-Python: >=3.5
Provides-Extra: test
